jsonjavascriptnotation/__init__.py
jsonjavascriptnotation/json_wrapper.py
jsonjavascriptnotation-0.1.6.dist-info/LICENSE
jsonjavascriptnotation-0.1.6.dist-info/METADATA
jsonjavascriptnotation-0.1.6.dist-info/WHEEL
jsonjavascriptnotation-0.1.6.dist-info/top_level.txt
jsonjavascriptnotation-0.1.6.dist-info/RECORD
