Metadata-Version: 2.1
Name: jsonjavascriptnotation
Version: 0.1.6
Summary: Access JSON using Javascript Object Notation.
Home-page: https://github.com/Emmerson-Miranda/jsonjavascriptnotation
Author: Emmerson Miranda
License: MIT
License-File: LICENSE
